quietcool/__init__.py
quietcool/api.py
quietcool/client.py
quietcool/device.py
quietcool-0.1.2.dist-info/METADATA
quietcool-0.1.2.dist-info/WHEEL
quietcool-0.1.2.dist-info/entry_points.txt
quietcool-0.1.2.dist-info/top_level.txt
quietcool-0.1.2.dist-info/RECORD
